{
  "schema": {
    "name": "mca-ai-enhanced.federation.round",
    "version": 2,
    "description": "One file per federation round: metadata + full aggregated tactics snapshot (privacy-safe)"
  },
  "privacy": {
    "personalData": false,
    "notes": [
      "No player identifiers (UUID/name/IP) are stored.",
      "No server identifiers are stored; only aggregate counts."
    ]
  },
  "semantics": {
    "contributors": {
      "meaning": "Aggregate counts only (no identifiers). `submissions` reflects distinct serverId+mobType contributions for the round; `servers` reflects distinct server contributors for the round."
    },
    "reward": {
      "meaning": "Average tactical reward signal emitted by the mod. This is an internal, unitless score used for ranking/pruning tactics.",
      "normalized": false,
      "units": "arbitrary",
      "notes": [
        "Reward is computed client-side and may change across mod versions.",
        "Do not assume a fixed numeric range; treat as relative within the same schema/version."
      ]
    },
    "success": {
      "meaning": "Per-action outcome tracking aggregated across contributing samples. Counts are always authoritative; rates are derived views.",
      "notes": [
        "`successCount` and `count` are the authoritative counts (successes and attempts).",
        "`rawSuccessRate` is the binomial rate derived from counts: successCount / count.",
        "`successRate` is a smoothed/blended score used for ranking/selection and may differ from rawSuccessRate.",
        "For low attempts, rates have low confidence; prefer using (successCount, count) over rate alone."
      ]
    }
  },
  "round": 1325,
  "timestamp": "2026-01-16T19:55:53.072Z",
  "contributors": {
    "servers": 1473,
    "submissions": 3
  },
  "mobTypes": [
    "pillager",
    "zombie"
  ],
  "modelStats": {
    "pillager": {
      "distinctActionsObserved": 2,
      "totalExperiences": 4,
      "legacy": {}
    },
    "zombie": {
      "distinctActionsObserved": 1,
      "totalExperiences": 1,
      "legacy": {}
    }
  },
  "aggregation": {
    "method": "FedAvg",
    "workerVersion": "3.0.0"
  },
  "tactics": {
    "pillager": {
      "patrol_route": {
        "avgReward": 8.67874999375,
        "count": 2,
        "successCount": 1,
        "successRate": 0.51875,
        "rawSuccessRate": 0.5,
        "success": {
          "successes": 1,
          "attempts": 2,
          "rate": 0.51875,
          "smoothedRate": 0.51875,
          "rawRate": 0.5
        },
        "legacy": {}
      },
      "straight_charge": {
        "avgReward": 0.10000000265625002,
        "count": 2,
        "successCount": 2,
        "successRate": 0.7213541666666667,
        "rawSuccessRate": 1,
        "success": {
          "successes": 2,
          "attempts": 2,
          "rate": 0.7213541666666667,
          "smoothedRate": 0.7213541666666667,
          "rawRate": 1
        },
        "legacy": {}
      }
    },
    "zombie": {
      "heartbeat_init": {
        "avgReward": 0.5,
        "count": 1,
        "successCount": 1,
        "successRate": 0.6,
        "rawSuccessRate": 1,
        "success": {
          "successes": 1,
          "attempts": 1,
          "rate": 0.6,
          "smoothedRate": 0.6,
          "rawRate": 1
        },
        "legacy": {}
      }
    }
  },
  "mobTypeSummary": {
    "pillager": {
      "distinctActionsObserved": 2,
      "topActions": [
        {
          "action": "patrol_route",
          "avgReward": 8.67874999375,
          "count": 2,
          "successCount": 1,
          "failureCount": 1,
          "successRate": 0.51875,
          "rawSuccessRate": 0.5
        },
        {
          "action": "straight_charge",
          "avgReward": 0.10000000265625002,
          "count": 2,
          "successCount": 2,
          "failureCount": 0,
          "successRate": 0.7213541666666667,
          "rawSuccessRate": 1
        }
      ]
    },
    "zombie": {
      "distinctActionsObserved": 1,
      "topActions": [
        {
          "action": "heartbeat_init",
          "avgReward": 0.5,
          "count": 1,
          "successCount": 1,
          "failureCount": 0,
          "successRate": 0.6,
          "rawSuccessRate": 1
        }
      ]
    }
  },
  "metadata": {
    "loggedAt": "2026-01-16T20:00:37.666Z",
    "source": "federation-coordinator",
    "version": "3.0.0"
  }
}